ctcsound7.py
ctcsound7/__init__.py
ctcsound7/_dll.py
ctcsound7/_util.py
ctcsound7/api6.py
ctcsound7/api7.py
ctcsound7/common.py
ctcsound7/extra.py
ctcsound7/py.typed
libcsound/__init__.py
libcsound/_dll.py
libcsound/_util.py
libcsound/api6.py
libcsound/api7.py
libcsound/common.py
libcsound/py.typed
libcsound-0.11.3.dist-info/METADATA
libcsound-0.11.3.dist-info/WHEEL
libcsound-0.11.3.dist-info/top_level.txt
libcsound-0.11.3.dist-info/RECORD
