Metadata-Version: 2.4
Name: libcsound
Version: 0.11.3
Summary: Python bindings to the Csound API, supporting all versions of csound higher or equal to 6.18, including csound 7
Author-email: Eduardo Moguillansky <eduardo.moguillansky@gmail.com>
License:                   GNU LESSER GENERAL PUBLIC LICENSE
Project-URL: Homepage, https://github.com/csound-plugins/libcsound
Keywords: csound
Classifier: Topic :: Multimedia :: Sound/Audio
Classifier: Programming Language :: Python :: 3
Classifier: Operating System :: OS Independent
Requires-Python: >=3.9
Requires-Dist: numpy>=1.24
